tagc/__init__.py
tagc/__main__.py
tagc/cal_thresh.py
tagc/cleaner.py
tagc/data_pipe.py
tagc/data_utils.py
tagc/dataset.py
tagc/domain.py
tagc/evaluation.py
tagc/io_utils.py
tagc/make_ds.py
tagc/make_figs.py
tagc/mask_explain.py
tagc/model.py
tagc/review.py
tagc/train.py
tagc/validation.py
tagc/visualization.py
tagc/web.py
tagc/web_utils.py
tagc-0.2.2.dist-info/WHEEL
tagc-0.2.2.dist-info/METADATA
tagc-0.2.2.dist-info/RECORD
