Metadata-Version: 2.1
Name: tagc
Version: 0.2.2
Summary: 
Author: Kiyoshi Mu
Author-email: mooyewtsing@gmail.com
Requires-Python: >=3.6.9,<4.0.0
Classifier: Programming Language :: Python :: 3
Classifier: Programming Language :: Python :: 3.7
Classifier: Programming Language :: Python :: 3.8
Classifier: Programming Language :: Python :: 3.9
Requires-Dist: dash (>=1.16.2,<2.0.0)
Requires-Dist: fire (>=0.3.1,<0.4.0)
Requires-Dist: kaleido (>=0.2.1,<0.3.0)
Requires-Dist: openpyxl (>=3.0.6,<4.0.0)
Requires-Dist: pandas (>=1.1.3,<2.0.0)
Requires-Dist: plotly (>=4.11.0,<5.0.0)
Requires-Dist: requests (>=2.24.0,<3.0.0)
Requires-Dist: scikit-learn (>=0.23.2,<0.24.0)
Requires-Dist: toolz (>=0.11.1,<0.12.0)
Requires-Dist: torch (==1.7.1)
Requires-Dist: tqdm (>=4.50.1,<5.0.0)
Requires-Dist: transformers (==3.5.1)
Requires-Dist: wheel (>=0.35.1,<0.36.0)
